{
 "ang": 101,
 "lines": [
  {
   "gurmukhi": "ਨਾਮ ਨਿਧਾਨ ਤਿਸਹਿ ਪਰਾਪਤਿ ਜਿਸੁ ਸਬਦੁ ਗੁਰੂ ਮਨਿ ਵੂਠਾ ਜੀਉ ॥੨॥",
   "translit": "naam nidhaan tiseh paraapat jis sabad guroo man vootthaa jeeo |2|",
   "english": "The Treasure of the Naam is obtained by one whose mind is filled with the Word of the Guru's Shabad. ||2||",
   "shabadId": "8Q6"
  },
  {
   "gurmukhi": "ਜੋ ਜੋ ਪੀਵੈ ਸੋ ਤ੍ਰਿਪਤਾਵੈ ॥",
   "translit": "jo jo peevai so tripataavai |",
   "english": "Whoever drinks this in, is satisfied.",
   "shabadId": "8Q6"
  },
  {
   "gurmukhi": "ਅਮਰੁ ਹੋਵੈ ਜੋ ਨਾਮ ਰਸੁ ਪਾਵੈ ॥",
   "translit": "amar hovai jo naam ras paavai |",
   "english": "Whoever obtains the Sublime Essence of the Naam becomes immortal.",
   "shabadId": "8Q6"
  },
  {
   "gurmukhi": "ਜਿਨਿ ਹਰਿ ਰਸੁ ਪਾਇਆ ਸੋ ਤ੍ਰਿਪਤਿ ਅਘਾਨਾ ॥",
   "translit": "jin har ras paaeaa so tripat aghaanaa |",
   "english": "One who obtains the Sublime Essence of the Lord is satisfied and fulfilled.",
   "shabadId": "8Q6"
  },
  {
   "gurmukhi": "ਜਿਨਿ ਹਰਿ ਸਾਦੁ ਪਾਇਆ ਸੋ ਨਾਹਿ ਡੁਲਾਨਾ ॥",
   "translit": "jin har saad paaeaa so naeh ddulaanaa |",
   "english": "One who obtains this Flavor of the Lord does not waver.",
   "shabadId": "8Q6"
  },
  {
   "gurmukhi": "ਤਿਸਹਿ ਪਰਾਪਤਿ ਹਰਿ ਹਰਿ ਨਾਮਾ ਜਿਸੁ ਮਸਤਕਿ ਭਾਗੀਠਾ ਜੀਉ ॥੩॥",
   "translit": "tiseh paraapat har har naamaa jis masatak bhaageetthaa jeeo |3|",
   "english": "One who has this destiny written on his forehead obtains the Name of the Lord, Har, Har. ||3||",
   "shabadId": "8Q6"
  },
  {
   "gurmukhi": "ਤਿਸੁ ਲਗਿ ਮੁਕਤੁ ਭਏ ਘਣੇਰੇ ॥",
   "translit": "tis lag mukat bhe ghanere |",
   "english": "Attached to Him, a great many have been liberated.",
   "shabadId": "8Q6"
  },
  {
   "gurmukhi": "ਨਾਮੁ ਨਿਧਾਨਾ ਗੁਰਮੁਖਿ ਪਾਈਐ ਕਹੁ ਨਾਨਕ ਵਿਰਲੀ ਡੀਠਾ ਜੀਉ ॥੪॥੧੫॥੨੨॥",
   "translit": "naam nidhaanaa guramukh paaeeai kahu naanak viralee ddeetthaa jeeo |4|15|22|",
   "english": "The Gurmukh obtains the Treasure of the Naam; says Nanak, those who see the Lord are very rare. ||4||15||22||",
   "shabadId": "8Q6"
  },
  {
   "gurmukhi": "ਹਰਿ ਇਕਸੁ ਹਥਿ ਆਇਆ ਵਰਸਾਣੇ ਬਹੁਤੇਰੇ ॥",
   "translit": "har ikas hath aaeaa varasaane bahutere |",
   "english": "The Lord has come into the hands of the One, the Guru, who has blessed so many with good fortune.",
   "shabadId": "8Q6"
  },
  {
   "gurmukhi": "ਮਾਝ ਮਹਲਾ ੫ ॥",
   "translit": "maajh mahalaa 5 |",
   "english": "Maajh, Fifth Mehl:",
   "shabadId": "AF5"
  },
  {
   "gurmukhi": "ਨਿਧਿ ਸਿਧਿ ਰਿਧਿ ਹਰਿ ਹਰਿ ਹਰਿ ਮੇਰੈ ॥",
   "translit": "nidh sidh ridh har har har merai |",
   "english": "My Lord, Har, Har, Har, is the nine treasures, the supernatural spiritual powers of the Siddhas, wealth and prosperity.",
   "shabadId": "AF5"
  },
  {
   "gurmukhi": "ਜਨਮੁ ਪਦਾਰਥੁ ਗਹਿਰ ਗੰਭੀਰੈ ॥",
   "translit": "janam padaarath gahir ganbheerai |",
   "english": "He is the Deep and Profound Treasure of Life.",
   "shabadId": "AF5"
  },
  {
   "gurmukhi": "ਲਾਖ ਕੋਟ ਖੁਸੀਆ ਰੰਗ ਰਾਵੈ ਜੋ ਗੁਰ ਲਾਗਾ ਪਾਈ ਜੀਉ ॥੧॥",
   "translit": "laakh kott khuseea rang raavai jo gur laagaa paaee jeeo |1|",
   "english": "Hundreds of thousands, even millions of pleasures and delights are enjoyed by one who falls at the Guru's Feet. ||1||",
   "shabadId": "AF5"
  },
  {
   "gurmukhi": "ਸਗਲ ਉਧਾਰੇ ਭਾਈ ਮੀਤਾ ॥",
   "translit": "sagal udhaare bhaaee meetaa |",
   "english": "and all family and friends are saved.",
   "shabadId": "AF5"
  },
  {
   "gurmukhi": "ਅਗਮ ਅਗੋਚਰੁ ਸੁਆਮੀ ਅਪੁਨਾ ਗੁਰ ਕਿਰਪਾ ਤੇ ਸਚੁ ਧਿਆਈ ਜੀਉ ॥੨॥",
   "translit": "agam agochar suaamee apunaa gur kirapaa te sach dhiaaee jeeo |2|",
   "english": "By Guru's Grace, I meditate on the Inaccessible and Unfathomable True Lord. ||2||",
   "shabadId": "AF5"
  },
  {
   "gurmukhi": "ਦਰਸਨੁ ਪੇਖਤ ਭਏ ਪੁਨੀਤਾ ॥",
   "translit": "darasan pekhat bhe puneetaa |",
   "english": "Gazing upon the Blessed Vision of His Darshan, all are sanctified,",
   "shabadId": "AF5"
  },
  {
   "gurmukhi": "ਵਡਭਾਗੀ ਦਰਸਨੁ ਕੋ ਵਿਰਲਾ ਪਾਏ ॥",
   "translit": "vaddabhaagee darasan ko viralaa paae |",
   "english": "By great good fortune, receive His Darshan.",
   "shabadId": "AF5"
  },
  {
   "gurmukhi": "ਜਾ ਕਉ ਖੋਜਹਿ ਸਰਬ ਉਪਾਏ ॥",
   "translit": "jaa kau khojeh sarab upaae |",
   "english": "The One, the Guru, who is sought by all-only a few,",
   "shabadId": "AF5"
  },
  {
   "gurmukhi": "ਊਚ ਅਪਾਰ ਅਗੋਚਰ ਥਾਨਾ ਓਹੁ ਮਹਲੁ ਗੁਰੂ ਦੇਖਾਈ ਜੀਉ ॥੩॥",
   "translit": "aooch apaar agochar thaanaa ohu mehal guroo dekhaaee jeeo |3|",
   "english": "His Place is lofty, infinite and unfathomable; the Guru has shown me that palace. ||3||",
   "shabadId": "AF5"
  },
  {
   "gurmukhi": "ਗਹਿਰ ਗੰਭੀਰ ਅੰਮ੍ਰਿਤ ਨਾਮੁ ਤੇਰਾ ॥",
   "translit": "gahir ganbheer amrit naam teraa |",
   "english": "Your Ambrosial Name is deep and profound.",
   "shabadId": "AF5"
  },
  {
   "gurmukhi": "ਮੁਕਤਿ ਭਇਆ ਜਿਸੁ ਰਿਦੈ ਵਸੇਰਾ ॥",
   "translit": "mukat bheaa jis ridai vaseraa |",
   "english": "That person is liberated, in whose heart You dwell.",
   "shabadId": "AF5"
  },
  {
   "gurmukhi": "ਗੁਰਿ ਬੰਧਨ ਤਿਨ ਕੇ ਸਗਲੇ ਕਾਟੇ ਜਨ ਨਾਨਕ ਸਹਜਿ ਸਮਾਈ ਜੀਉ ॥੪॥੧੬॥੨੩॥",
   "translit": "gur bandhan tin ke sagale kaatte jan naanak sehaj samaaee jeeo |4|16|23|",
   "english": "The Guru cuts away all his bonds; O Servant Nanak, he is absorbed in the poise of intuitive peace. ||4||16||23||",
   "shabadId": "AF5"
  },
  {
   "gurmukhi": "ਪ੍ਰਭ ਕਿਰਪਾ ਤੇ ਹਰਿ ਹਰਿ ਧਿਆਵਉ ॥",
   "translit": "prabh kirapaa te har har dhiaavau |",
   "english": "By God's Grace, I meditate on the Lord, Har, Har.",
   "shabadId": "Q5A"
  },
  {
   "gurmukhi": "ਪ੍ਰਭੂ ਦਇਆ ਤੇ ਮੰਗਲੁ ਗਾਵਉ ॥",
   "translit": "prabhoo deaa te mangal gaavau |",
   "english": "By God's Kindness, I sing the songs of joy.",
   "shabadId": "Q5A"
  },
  {
   "gurmukhi": "ਮਾਝ ਮਹਲਾ ੫ ॥",
   "translit": "maajh mahalaa 5 |",
   "english": "Maajh, Fifth Mehl:",
   "shabadId": "Q5A"
  },
  {
   "gurmukhi": "ਨਾਮੁ ਅਉਖਧੁ ਮੋ ਕਉ ਸਾਧੂ ਦੀਆ ॥",
   "translit": "naam aaukhadh mo kau saadhoo deea |",
   "english": "The Holy Saint has given me the Medicine of the Naam.",
   "shabadId": "Q5A"
  },
  {
   "gurmukhi": "ਊਠਤ ਬੈਠਤ ਸੋਵਤ ਜਾਗਤ ਹਰਿ ਧਿਆਈਐ ਸਗਲ ਅਵਰਦਾ ਜੀਉ ॥੧॥",
   "translit": "aootthat baitthat sovat jaagat har dhiaaeeai sagal avaradaa jeeo |1|",
   "english": "While standing and sitting, while sleeping and while awake, meditate on the Lord, all your life. ||1||",
   "shabadId": "Q5A"
  },
  {
   "gurmukhi": "ਕਿਲਬਿਖ ਕਾਟੇ ਨਿਰਮਲੁ ਥੀਆ ॥",
   "translit": "kilabikh kaatte niramal theea |",
   "english": "My sins have been cut out, and I have become pure.",
   "shabadId": "Q5A"
  },
  {
   "gurmukhi": "ਅਨਦੁ ਭਇਆ ਨਿਕਸੀ ਸਭ ਪੀਰਾ ਸਗਲ ਬਿਨਾਸੇ ਦਰਦਾ ਜੀਉ ॥੨॥",
   "translit": "anad bheaa nikasee sabh peeraa sagal binaase daradaa jeeo |2|",
   "english": "I am filled with bliss, and all my pains have been taken away. All my suffering has been dispelled. ||2||",
   "shabadId": "Q5A"
  },
  {
   "gurmukhi": "ਸਤਿ ਕਰੇ ਜਿਨਿ ਗੁਰੂ ਪਛਾਤਾ ਸੋ ਕਾਹੇ ਕਉ ਡਰਦਾ ਜੀਉ ॥੩॥",
   "translit": "sat kare jin guroo pachhaataa so kaahe kau ddaradaa jeeo |3|",
   "english": "One who recognizes the Guru practices Truth; why should he be afraid? ||3||",
   "shabadId": "Q5A"
  },
  {
   "gurmukhi": "ਜਿਸ ਕਾ ਅੰਗੁ ਕਰੇ ਮੇਰਾ ਪਿਆਰਾ ॥",
   "translit": "jis kaa ang kare meraa piaaraa |",
   "english": "One who has my Beloved on his side,",
   "shabadId": "Q5A"
  },
  {
   "gurmukhi": "ਸੋ ਮੁਕਤਾ ਸਾਗਰ ਸੰਸਾਰਾ ॥",
   "translit": "so mukataa saagar sansaaraa |",
   "english": "Is liberated from the world-ocean.",
   "shabadId": "Q5A"
  },
  {
   "gurmukhi": "ਸਾਸਿ ਸਾਸਿ ਹਰਿ ਗਾਵੈ ਨਾਨਕੁ ਸਤਿਗੁਰ ਢਾਕਿ ਲੀਆ ਮੇਰਾ ਪੜਦਾ ਜੀਉ ॥੪॥੧੭॥੨੪॥",
   "translit": "saas saas har gaavai naanak satigur dtaak leea meraa parradaa jeeo |4|17|24|",
   "english": "With each and every breath, Nanak sings the Lord's Praises. The True Guru has covered my sins. ||4||17||24||",
   "shabadId": "Q5A"
  },
  {
   "gurmukhi": "ਗੁਰ ਭੇਟਤ ਹਉ ਗਈ ਬਲਾਏ ॥",
   "translit": "gur bhettat hau gee balaae |",
   "english": "The demon of pride has departed.",
   "shabadId": "Q5A"
  },
  {
   "gurmukhi": "ਜਬ ਤੇ ਸਾਧੂ ਸੰਗਤਿ ਪਾਏ ॥",
   "translit": "jab te saadhoo sangat paae |",
   "english": "Since I found the Company of the Holy and met the Guru,",
   "shabadId": "Q5A"
  },
  {
   "gurmukhi": "ਓਤਿ ਪੋਤਿ ਸੇਵਕ ਸੰਗਿ ਰਾਤਾ ॥",
   "translit": "ot pot sevak sang raataa |",
   "english": "Through and through, the Lord is intermingled with His servant.",
   "shabadId": "N5V"
  },
  {
   "gurmukhi": "ਮਾਝ ਮਹਲਾ ੫ ॥",
   "translit": "maajh mahalaa 5 |",
   "english": "Maajh, Fifth Mehl:",
   "shabadId": "N5V"
  },
  {
   "gurmukhi": "ਪ੍ਰਭ ਪ੍ਰਤਿਪਾਲੇ ਸੇਵਕ ਸੁਖਦਾਤਾ ॥",
   "translit": "prabh pratipaale sevak sukhadaataa |",
   "english": "God, the Giver of Peace, cherishes His servant.",
   "shabadId": "N5V"
  },
  {
   "gurmukhi": "ਪਾਣੀ ਪਖਾ ਪੀਸਉ ਸੇਵਕ ਕੈ ਠਾਕੁਰ ਹੀ ਕਾ ਆਹਰੁ ਜੀਉ ॥੧॥",
   "translit": "paanee pakhaa peesau sevak kai tthaakur hee kaa aahar jeeo |1|",
   "english": "I carry the water, wave the fan, and grind the grain for the servant of my Lord and Master. ||1||",
   "shabadId": "N5V"
  },
  {
   "gurmukhi": "ਕਾਟਿ ਸਿਲਕ ਪ੍ਰਭਿ ਸੇਵਾ ਲਾਇਆ ॥",
   "translit": "kaatt silak prabh sevaa laaeaa |",
   "english": "God has cut the noose from around my neck; He has placed me in His Service.",
   "shabadId": "N5V"
  },
  {
   "gurmukhi": "ਸੋਈ ਕਮਾਵੈ ਜੋ ਸਾਹਿਬ ਭਾਵੈ ਸੇਵਕੁ ਅੰਤਰਿ ਬਾਹਰਿ ਮਾਹਰੁ ਜੀਉ ॥੨॥",
   "translit": "soee kamaavai jo saahib bhaavai sevak antar baahar maahar jeeo |2|",
   "english": "He does that which pleases his Lord and Master. Inwardly and outwardly, the servant knows his Lord. ||2||",
   "shabadId": "N5V"
  },
  {
   "gurmukhi": "ਹੁਕਮੁ ਸਾਹਿਬ ਕਾ ਸੇਵਕ ਮਨਿ ਭਾਇਆ ॥",
   "translit": "hukam saahib kaa sevak man bhaaeaa |",
   "english": "The Lord and Master's Command is pleasing to the mind of His servant.",
   "shabadId": "N5V"
  },
  {
   "gurmukhi": "ਤੂੰ ਦਾਨਾ ਠਾਕੁਰੁ ਸਭ ਬਿਧਿ ਜਾਨਹਿ ॥",
   "translit": "toon daanaa tthaakur sabh bidh jaaneh |",
   "english": "You are the All-knowing Lord and Master; You know all ways and means.",
   "shabadId": "N5V"
  }
 ]
}