{
 "ang": 943,
 "lines": [
  {
   "gurmukhi": "ਅਕਥ ਕਥਾ ਲੇ ਰਹਉ ਨਿਰਾਲਾ ॥",
   "translit": "akath kathaa le rhau niraalaa |",
   "english": "Speaking the Unspoken Speech, I remain unattached.",
   "shabadId": "TNS"
  },
  {
   "gurmukhi": "ਪਵਨ ਅਰੰਭੁ ਸਤਿਗੁਰ ਮਤਿ ਵੇਲਾ ॥",
   "translit": "pavan aranbh satigur mat velaa |",
   "english": "From the air came the beginning. This is the age of the True Guru's Teachings.",
   "shabadId": "TNS"
  },
  {
   "gurmukhi": "ਸਬਦੁ ਗੁਰੂ ਸੁਰਤਿ ਧੁਨਿ ਚੇਲਾ ॥",
   "translit": "sabad guroo surat dhun chelaa |",
   "english": "The Shabad is the Guru, upon whom I lovingly focus my consciousness; I am the chaylaa, the disciple.",
   "shabadId": "TNS"
  },
  {
   "gurmukhi": "ਨਾਨਕ ਜੁਗਿ ਜੁਗਿ ਗੁਰ ਗੋਪਾਲਾ ॥",
   "translit": "naanak jug jug gur gopaalaa |",
   "english": "O Nanak, throughout the ages, the Lord of the World is my Guru.",
   "shabadId": "TNS"
  },
  {
   "gurmukhi": "ਏਕੁ ਸਬਦੁ ਜਿਤੁ ਕਥਾ ਵੀਚਾਰੀ ॥",
   "translit": "ek sabad jit kathaa veechaaree |",
   "english": "I contemplate the sermon of the Shabad, the Word of the One God.",
   "shabadId": "TNS"
  },
  {
   "gurmukhi": "ਗੁਰਮੁਖਿ ਹਉਮੈ ਅਗਨਿ ਨਿਵਾਰੀ ॥੪੪॥",
   "translit": "guramukh haumai agan nivaaree |44|",
   "english": "The Gurmukh puts out the fire of egotism. ||44||",
   "shabadId": "TNS"
  },
  {
   "gurmukhi": "ਮੈਣ ਕੇ ਦੰਤ ਕਿਉ ਖਾਈਐ ਸਾਰੁ ॥",
   "translit": "main ke dant kiau khaaeeai saar |",
   "english": "\"With teeth of wax, how can one chew iron?",
   "shabadId": "68X"
  },
  {
   "gurmukhi": "ਜਿਤੁ ਗਰਬੁ ਜਾਇ ਸੁ ਕਵਣੁ ਆਹਾਰੁ ॥",
   "translit": "jit garab jaae su kavan aahaar |",
   "english": "What is that food, which takes away pride?",
   "shabadId": "68X"
  },
  {
   "gurmukhi": "ਇਤ ਉਤ ਕਿਸ ਕਉ ਜਾਣਿ ਸਮਾਵੈ ॥",
   "translit": "eit ut kis kau jaan samaavai |",
   "english": "Who should we know to be pervading here and there?",
   "shabadId": "68X"
  },
  {
   "gurmukhi": "ਕਵਨ ਗੁਫਾ ਜਿਤੁ ਰਹੈ ਅਵਾਹਨੁ ॥",
   "translit": "kavan gufaa jit rahai avaahan |",
   "english": "Where is that cave, within which one may remain unshaken?",
   "shabadId": "68X"
  },
  {
   "gurmukhi": "ਹਿਵੈ ਕਾ ਘਰੁ ਮੰਦਰੁ ਅਗਨਿ ਪਿਰਾਹਨੁ ॥",
   "translit": "hivai kaa ghar mandar agan piraahan |",
   "english": "How can one live in the palace, the home of snow, wearing robes of fire?",
   "shabadId": "68X"
  },
  {
   "gurmukhi": "ਦੂਜਾ ਮੇਟੈ ਏਕੋ ਹੋਵੈ ॥",
   "translit": "doojaa mettai eko hovai |",
   "english": "and erasing duality, the mortal becomes one with God.",
   "shabadId": "68X"
  },
  {
   "gurmukhi": "ਕਵਨ ਧਿਆਨੁ ਮਨੁ ਮਨਹਿ ਸਮਾਵੈ ॥੪੫॥",
   "translit": "kavan dhiaan man maneh samaavai |45|",
   "english": "What is that meditation, which leads the mind to be absorbed in itself?\" ||45||",
   "shabadId": "68X"
  },
  {
   "gurmukhi": "ਹਉ ਹਉ ਮੈ ਮੈ ਵਿਚਹੁ ਖੋਵੈ ॥",
   "translit": "hau hau mai mai vichahu khovai |",
   "english": "Eradicating egotism and individualism from within,",
   "shabadId": "68X"
  },
  {
   "gurmukhi": "ਅੰਤਰਿ ਬਾਹਰਿ ਏਕੋ ਜਾਣੈ ॥",
   "translit": "antar baahar eko jaanai |",
   "english": "Know the One Lord, inside and out.",
   "shabadId": "68X"
  },
  {
   "gurmukhi": "ਜਗੁ ਕਰੜਾ ਮਨਮੁਖੁ ਗਾਵਾਰੁ ॥",
   "translit": "jag kararraa manamukh gaavaar |",
   "english": "The world is difficult for the foolish, self-willed manmukh;",
   "shabadId": "68X"
  },
  {
   "gurmukhi": "ਸਬਦੁ ਕਮਾਈਐ ਖਾਈਐ ਸਾਰੁ ॥",
   "translit": "sabad kamaaeeai khaaeeai saar |",
   "english": "practicing the Shabad, one chews iron.",
   "shabadId": "68X"
  },
  {
   "gurmukhi": "ਨਾਨਕ ਅਗਨਿ ਮਰੈ ਸਤਿਗੁਰ ਕੈ ਭਾਣੈ ॥੪੬॥",
   "translit": "naanak agan marai satigur kai bhaanai |46|",
   "english": "O Nanak, the fire is quenched, through the Pleasure of the True Guru's Will. ||46||",
   "shabadId": "68X"
  },
  {
   "gurmukhi": "ਸਬਦੁ ਵਸੈ ਸਚੁ ਅੰਤਰਿ ਹੀਆ ॥",
   "translit": "sabad vasai sach antar heea |",
   "english": "With the True Shabad abiding deep within the heart,",
   "shabadId": "BE4"
  },
  {
   "gurmukhi": "ਏਕੋ ਜਾਤਾ ਸਬਦੁ ਵੀਚਾਰੈ ॥",
   "translit": "eko jaataa sabad veechaarai |",
   "english": "realize that He is One, and contemplate the Shabad.",
   "shabadId": "BE4"
  },
  {
   "gurmukhi": "ਸਚ ਭੈ ਰਾਤਾ ਗਰਬੁ ਨਿਵਾਰੈ ॥",
   "translit": "sach bhai raataa garab nivaarai |",
   "english": "Imbued with the True Fear of God, pride is taken away;",
   "shabadId": "BE4"
  },
  {
   "gurmukhi": "ਤਨੁ ਮਨੁ ਸੀਤਲੁ ਰੰਗਿ ਰੰਗੀਆ ॥",
   "translit": "tan man seetal rang rangeea |",
   "english": "the body and mind are cooled and soothed, and colored with the Lord's Love.",
   "shabadId": "BE4"
  },
  {
   "gurmukhi": "ਨਾਨਕ ਨਦਰੀ ਨਦਰਿ ਪਿਆਰੇ ॥੪੭॥",
   "translit": "naanak nadaree nadar piaare |47|",
   "english": "O Nanak, the Beloved bestows His Glance of Grace. ||47||",
   "shabadId": "BE4"
  },
  {
   "gurmukhi": "ਕਾਮੁ ਕ੍ਰੋਧੁ ਬਿਖੁ ਅਗਨਿ ਨਿਵਾਰੇ ॥",
   "translit": "kaam krodh bikh agan nivaare |",
   "english": "The fire of sexual desire, anger and corruption is quenched.",
   "shabadId": "BE4"
  },
  {
   "gurmukhi": "ਕਵਨ ਮੁਖਿ ਸੂਰਜੁ ਤਪੈ ਤਪਾਇਆ ॥",
   "translit": "kavan mukh sooraj tapai tapaaeaa |",
   "english": "How does the sun blaze so brilliantly?",
   "shabadId": "BE4"
  },
  {
   "gurmukhi": "ਕਵਨ ਮੁਖਿ ਕਾਲੁ ਜੋਹਤ ਨਿਤ ਰਹੈ ॥",
   "translit": "kavan mukh kaal johat nit rahai |",
   "english": "How can the constant watchful gaze of Death be turned away?",
   "shabadId": "BE4"
  },
  {
   "gurmukhi": "ਕਵਨ ਮੁਖਿ ਚੰਦੁ ਹਿਵੈ ਘਰੁ ਛਾਇਆ ॥",
   "translit": "kavan mukh chand hivai ghar chhaaeaa |",
   "english": "\"The moon of the mind is cool and dark; how is it enlightened?",
   "shabadId": "BE4"
  },
  {
   "gurmukhi": "ਬੋਲੈ ਬਾਣੀ ਨਾਨਕੁ ਬੀਚਾਰੈ ॥੪੮॥",
   "translit": "bolai baanee naanak beechaarai |48|",
   "english": "Give us your thoughtful reply, O Nanak.\" ||48||",
   "shabadId": "BE4"
  },
  {
   "gurmukhi": "ਕਵਨੁ ਜੋਧੁ ਜੋ ਕਾਲੁ ਸੰਘਾਰੈ ॥",
   "translit": "kavan jodh jo kaal sanghaarai |",
   "english": "Who is the warrior, who conquers Death?",
   "shabadId": "BE4"
  },
  {
   "gurmukhi": "ਕਵਨ ਬੁਧਿ ਗੁਰਮੁਖਿ ਪਤਿ ਰਹੈ ॥",
   "translit": "kavan budh guramukh pat rahai |",
   "english": "By what understanding is the honor of the Gurmukh preserved?",
   "shabadId": "BE4"
  },
  {
   "gurmukhi": "ਸਸਿ ਘਰਿ ਸੂਰੁ ਵਸੈ ਮਿਟੈ ਅੰਧਿਆਰਾ ॥",
   "translit": "sas ghar soor vasai mittai andhiaaraa |",
   "english": "When the sun dwells in the house of the moon, the darkness is dispelled.",
   "shabadId": "EHD"
  },
  {
   "gurmukhi": "ਸਬਦੁ ਭਾਖਤ ਸਸਿ ਜੋਤਿ ਅਪਾਰਾ ॥",
   "translit": "sabad bhaakhat sas jot apaaraa |",
   "english": "Giving voice to the Shabad, the moon of the mind is illuminated with infinity.",
   "shabadId": "EHD"
  },
  {
   "gurmukhi": "ਸੁਖੁ ਦੁਖੁ ਸਮ ਕਰਿ ਨਾਮੁ ਅਧਾਰਾ ॥",
   "translit": "sukh dukh sam kar naam adhaaraa |",
   "english": "Pleasure and pain are just the same, when one takes the Support of the Naam, the Name of the Lord.",
   "shabadId": "EHD"
  },
  {
   "gurmukhi": "ਆਪੇ ਪਾਰਿ ਉਤਾਰਣਹਾਰਾ ॥",
   "translit": "aape paar utaaranahaaraa |",
   "english": "He Himself saves, and carries us across.",
   "shabadId": "EHD"
  },
  {
   "gurmukhi": "ਪ੍ਰਣਵਤਿ ਨਾਨਕੁ ਕਾਲੁ ਨ ਖਾਇ ॥੪੯॥",
   "translit": "pranavat naanak kaal na khaae |49|",
   "english": "and then, prays Nanak, one is not consumed by Death. ||49||",
   "shabadId": "EHD"
  },
  {
   "gurmukhi": "ਗੁਰ ਪਰਚੈ ਮਨੁ ਸਾਚਿ ਸਮਾਇ ॥",
   "translit": "gur parachai man saach samaae |",
   "english": "With faith in the Guru, the mind merges in Truth,",
   "shabadId": "EHD"
  },
  {
   "gurmukhi": "ਬਿਨੁ ਨਾਵੈ ਦੁਖੁ ਕਾਲੁ ਸੰਤਾਪੈ ॥",
   "translit": "bin naavai dukh kaal santaapai |",
   "english": "Without the Name, one is afflicted by pain and death.",
   "shabadId": "EHD"
  },
  {
   "gurmukhi": "ਨਾਮ ਤਤੁ ਸਭ ਹੀ ਸਿਰਿ ਜਾਪੈ ॥",
   "translit": "naam tat sabh hee sir jaapai |",
   "english": "The essence of the Naam, the Name of the Lord, is known to be the most exalted and excellent of all.",
   "shabadId": "EHD"
  },
  {
   "gurmukhi": "ਤਤੋ ਤਤੁ ਮਿਲੈ ਮਨੁ ਮਾਨੈ ॥",
   "translit": "tato tat milai man maanai |",
   "english": "When one's essence merges into the essence, the mind is satisfied and fulfilled.",
   "shabadId": "EHD"
  },
  {
   "gurmukhi": "ਬੋਲੈ ਪਵਨਾ ਗਗਨੁ ਗਰਜੈ ॥",
   "translit": "bolai pavanaa gagan garajai |",
   "english": "The breath blows across the sky of the Tenth Gate and vibrates.",
   "shabadId": "EHD"
  },
  {
   "gurmukhi": "ਦੂਜਾ ਜਾਇ ਇਕਤੁ ਘਰਿ ਆਨੈ ॥",
   "translit": "doojaa jaae ikat ghar aanai |",
   "english": "Duality is gone, and one enters into the home of the One Lord.",
   "shabadId": "EHD"
  },
  {
   "gurmukhi": "ਨਾਨਕ ਨਿਹਚਲੁ ਮਿਲਣੁ ਸਹਜੈ ॥੫੦॥",
   "translit": "naanak nihachal milan sahajai |50|",
   "english": "O Nanak, the mortal then intuitively meets the eternal, unchanging Lord. ||50||",
   "shabadId": "EHD"
  },
  {
   "gurmukhi": "ਚਉਥੇ ਸੁੰਨੈ ਜੋ ਨਰੁ ਜਾਣੈ ਤਾ ਕਉ ਪਾਪੁ ਨ ਪੁੰਨੰ ॥",
   "translit": "chauthe sunai jo nar jaanai taa kau paap na punan |",
   "english": "One who knows the Lord in the fourth state, is not subject to virtue or vice.",
   "shabadId": "74L"
  },
  {
   "gurmukhi": "ਅੰਤਰਿ ਸੁੰਨੰ ਬਾਹਰਿ ਸੁੰਨੰ ਤ੍ਰਿਭਵਣ ਸੁੰਨ ਮਸੁੰਨੰ ॥",
   "translit": "antar sunan baahar sunan tribhavan sun masunan |",
   "english": "The absolute Lord is deep within; the absolute Lord is outside us as well. The absolute Lord totally fills the three worlds.",
   "shabadId": "74L"
  },
  {
   "gurmukhi": "ਆਦਿ ਪੁਰਖੁ ਨਿਰੰਜਨ ਦੇਉ ॥",
   "translit": "aad purakh niranjan deo |",
   "english": "Knows the Primal Being, the Immaculate Divine Lord.",
   "shabadId": "74L"
  },
  {
   "gurmukhi": "ਨਾਨਕ ਸੋਈ ਪੁਰਖੁ ਬਿਧਾਤਾ ॥੫੧॥",
   "translit": "naanak soee purakh bidhaataa |51|",
   "english": "O Nanak, is himself the Primal Lord, the Architect of Destiny. ||51||",
   "shabadId": "74L"
  },
  {
   "gurmukhi": "ਜੋ ਜਨੁ ਨਾਮ ਨਿਰੰਜਨ ਰਾਤਾ ॥",
   "translit": "jo jan naam niranjan raataa |",
   "english": "That humble being who is imbued with the Immaculate Naam,",
   "shabadId": "74L"
  },
  {
   "gurmukhi": "ਘਟਿ ਘਟਿ ਸੁੰਨ ਕਾ ਜਾਣੈ ਭੇਉ ॥",
   "translit": "ghatt ghatt sun kaa jaanai bheo |",
   "english": "One who knows the mystery of God the Absolute, who pervades each and every heart,",
   "shabadId": "74L"
  },
  {
   "gurmukhi": "ਸੁੰਨੋ ਸੁੰਨੁ ਕਹੈ ਸਭੁ ਕੋਈ ॥",
   "translit": "suno sun kahai sabh koee |",
   "english": "\"Everyone speaks of the Absolute Lord, the unmanifest void.",
   "shabadId": "74L"
  },
  {
   "gurmukhi": "ਅਨਹਤ ਸੁੰਨਿ ਰਤੇ ਸੇ ਕੈਸੇ ॥",
   "translit": "anahat sun rate se kaise |",
   "english": "Who are they, who are attuned to this absolute void?\"",
   "shabadId": "74L"
  },
  {
   "gurmukhi": "ਅਨਹਤ ਸੁੰਨੁ ਕਹਾ ਤੇ ਹੋਈ ॥",
   "translit": "anahat sun kahaa te hoee |",
   "english": "How can one find this absolute void?",
   "shabadId": "74L"
  },
  {
   "gurmukhi": "ਜਿਸ ਤੇ ਉਪਜੇ ਤਿਸ ਹੀ ਜੈਸੇ ॥",
   "translit": "jis te upaje tis hee jaise |",
   "english": "They are like the Lord, from whom they originated.",
   "shabadId": "74L"
  },
  {
   "gurmukhi": "ਓਇ ਜਨਮਿ ਨ ਮਰਹਿ ਨ ਆਵਹਿ ਜਾਹਿ ॥",
   "translit": "oe janam na mareh na aaveh jaeh |",
   "english": "They are not born, they do not die; they do not come and go.",
   "shabadId": "74L"
  },
  {
   "gurmukhi": "ਨਾਨਕ ਗੁਰਮੁਖਿ ਮਨੁ ਸਮਝਾਹਿ ॥੫੨॥",
   "translit": "naanak guramukh man samajhaeh |52|",
   "english": "O Nanak, the Gurmukhs instruct their minds. ||52||",
   "shabadId": "74L"
  },
  {
   "gurmukhi": "ਨਉ ਸਰ ਸੁਭਰ ਦਸਵੈ ਪੂਰੇ ॥",
   "translit": "nau sar subhar dasavai poore |",
   "english": "By practicing control over the nine gates, one attains perfect control over the Tenth Gate.",
   "shabadId": "9F7"
  },
  {
   "gurmukhi": "ਤਹ ਅਨਹਤ ਸੁੰਨ ਵਜਾਵਹਿ ਤੂਰੇ ॥",
   "translit": "teh anahat sun vajaaveh toore |",
   "english": "There, the unstruck sound current of the absolute Lord vibrates and resounds.",
   "shabadId": "9F7"
  },
  {
   "gurmukhi": "ਘਟਿ ਘਟਿ ਸਾਚੁ ਰਹਿਆ ਭਰਪੂਰੇ ॥",
   "translit": "ghatt ghatt saach rahiaa bharapoore |",
   "english": "The True Lord is pervading and permeating each and every heart.",
   "shabadId": "9F7"
  },
  {
   "gurmukhi": "ਸਾਚੈ ਰਾਚੇ ਦੇਖਿ ਹਜੂਰੇ ॥",
   "translit": "saachai raache dekh hajoore |",
   "english": "Behold the True Lord ever-present, and merge with Him.",
   "shabadId": "9F7"
  }
 ]
}