{
 "ang": 1035,
 "lines": [
  {
   "gurmukhi": "ਮੰਨੇ ਨਾਉ ਸੋਈ ਜਿਣਿ ਜਾਸੀ ਆਪੇ ਸਾਚੁ ਦ੍ਰਿੜਾਇਦਾ ॥੧੦॥",
   "translit": "mane naau soee jin jaasee aape saach drirraaeidaa |10|",
   "english": "Whoever believes in the Name, wins; He Himself implants Truth within. ||10||",
   "shabadId": "F8D"
  },
  {
   "gurmukhi": "ਸਾਧਿਕ ਸਾਚ ਭਲੇ ਵੀਚਾਰੇ ॥",
   "translit": "saadhik saach bhale veechaare |",
   "english": "The seekers of Truth and goodness contemplate You.",
   "shabadId": "F8D"
  },
  {
   "gurmukhi": "ਹਮ ਦਾਸਨ ਕੇ ਦਾਸ ਪਿਆਰੇ ॥",
   "translit": "ham daasan ke daas piaare |",
   "english": "I am the slave of Your slaves, O my Beloved.",
   "shabadId": "F8D"
  },
  {
   "gurmukhi": "ਪਲੈ ਸਾਚੁ ਸਚੇ ਸਚਿਆਰਾ ॥",
   "translit": "palai saach sache sachiaaraa |",
   "english": "The Truest of the True has the Truth is His lap.",
   "shabadId": "F8D"
  },
  {
   "gurmukhi": "ਸਾਚੇ ਭਾਵੈ ਸਬਦੁ ਪਿਆਰਾ ॥",
   "translit": "saache bhaavai sabad piaaraa |",
   "english": "The True Lord is pleased with those who love the Shabad.",
   "shabadId": "F8D"
  },
  {
   "gurmukhi": "ਗੁਰ ਬਿਨੁ ਸੋਝੀ ਕਿਨੈ ਨ ਹੋਈ ॥",
   "translit": "gur bin sojhee kinai na hoee |",
   "english": "Without the Guru, no one understands Him.",
   "shabadId": "F8D"
  },
  {
   "gurmukhi": "ਵਡਾ ਵਡਾ ਆਖੈ ਸਭੁ ਕੋਈ ॥",
   "translit": "vaddaa vaddaa aakhai sabh koee |",
   "english": "Everyone calls Him the greatest of the great.",
   "shabadId": "F8D"
  },
  {
   "gurmukhi": "ਤ੍ਰਿਭਵਣਿ ਸਾਚੁ ਕਲਾ ਧਰਿ ਥਾਪੀ ਸਾਚੇ ਹੀ ਪਤੀਆਇਦਾ ॥੧੧॥",
   "translit": "tribhavan saach kalaa dhar thaapee saache hee pateeaeidaa |11|",
   "english": "Exerting His power, the Lord has established Truth throughout the three worlds; with Truth He is pleased. ||11||",
   "shabadId": "F8D"
  },
  {
   "gurmukhi": "ਧੁਰਹੁ ਵਿਛੁੰਨੇ ਧਾਹੀ ਰੁੰਨੇ ॥",
   "translit": "dhurahu vichhune dhaahee rune |",
   "english": "Separated from the Primal Lord, they loudly weep and wail.",
   "shabadId": "F8D"
  },
  {
   "gurmukhi": "ਸਾਚਿ ਮਿਲੈ ਸੋ ਸਾਚੇ ਭਾਏ ਨਾ ਵੀਛੁੜਿ ਦੁਖੁ ਪਾਇਦਾ ॥੧੨॥",
   "translit": "saach milai so saache bhaae naa veechhurr dukh paaeidaa |12|",
   "english": "The True Lord is pleased with those who merge in Truth; they are not separated again, and they do not suffer. ||12||",
   "shabadId": "F8D"
  },
  {
   "gurmukhi": "ਜਿਸੁ ਬਖਸੇ ਤਿਸੁ ਦੇ ਵਡਿਆਈ ਮੇਲਿ ਨ ਪਛੋਤਾਇਦਾ ॥੧੩॥",
   "translit": "jis bakhase tis de vaddiaaee mel na pachhotaaeidaa |13|",
   "english": "He blesses those whom He forgives with glorious greatness; united with Him, they do not regret or repent. ||13 |",
   "shabadId": "F8D"
  },
  {
   "gurmukhi": "ਮਰਿ ਮਰਿ ਜਨਮਹਿ ਮੁਹਲਤਿ ਪੁੰਨੇ ॥",
   "translit": "mar mar janameh muhalat pune |",
   "english": "They die and die, only to be reborn, when their time has passed.",
   "shabadId": "F8D"
  },
  {
   "gurmukhi": "ਆਪੇ ਕਰਤਾ ਆਪੇ ਭੁਗਤਾ ॥",
   "translit": "aape karataa aape bhugataa |",
   "english": "| He Himself is the Creator, and He Himself is the Enjoyer.",
   "shabadId": "F8D"
  },
  {
   "gurmukhi": "ਆਪੇ ਮੁਕਤਿ ਦਾਨੁ ਮੁਕਤੀਸਰੁ ਮਮਤਾ ਮੋਹੁ ਚੁਕਾਇਦਾ ॥੧੪॥",
   "translit": "aape mukat daan mukateesar mamataa mohu chukaaeidaa |14|",
   "english": "The Lord of liberation Himself grants liberation; He eradicates possessiveness and attachment. ||14||",
   "shabadId": "F8D"
  },
  {
   "gurmukhi": "ਆਪੇ ਤ੍ਰਿਪਤਾ ਆਪੇ ਮੁਕਤਾ ॥",
   "translit": "aape tripataa aape mukataa |",
   "english": "He Himself is satisfied, and He Himself is liberated.",
   "shabadId": "F8D"
  },
  {
   "gurmukhi": "ਦਾਨਾ ਕੈ ਸਿਰਿ ਦਾਨੁ ਵੀਚਾਰਾ ॥",
   "translit": "daanaa kai sir daan veechaaraa |",
   "english": "I consider Your gifts to be the most wonderful gifts.",
   "shabadId": "F8D"
  },
  {
   "gurmukhi": "ਕਰਿ ਕਰਿ ਵੇਖੈ ਕੀਤਾ ਅਪਣਾ ਕਰਣੀ ਕਾਰ ਕਰਾਇਦਾ ॥੧੫॥",
   "translit": "kar kar vekhai keetaa apanaa karanee kaar karaaeidaa |15|",
   "english": "Creating the creation, You gaze upon what You have created; You cause all to do their deeds. ||15||",
   "shabadId": "F8D"
  },
  {
   "gurmukhi": "ਕਰਣ ਕਾਰਣ ਸਮਰਥੁ ਅਪਾਰਾ ॥",
   "translit": "karan kaaran samarath apaaraa |",
   "english": "You are the Cause of causes, Almighty Infinite Lord.",
   "shabadId": "F8D"
  },
  {
   "gurmukhi": "ਤੁਝ ਤੇ ਉਪਜਹਿ ਤੁਝ ਮਾਹਿ ਸਮਾਵਹਿ ॥",
   "translit": "tujh te upajeh tujh maeh samaaveh |",
   "english": "They issue forth from You, and merge again into You.",
   "shabadId": "F8D"
  },
  {
   "gurmukhi": "ਸੇ ਗੁਣ ਗਾਵਹਿ ਸਾਚੇ ਭਾਵਹਿ ॥",
   "translit": "se gun gaaveh saache bhaaveh |",
   "english": "They alone sing Your Glorious Praises, who are pleasing to You, O True Lord.",
   "shabadId": "F8D"
  },
  {
   "gurmukhi": "ਨਾਨਕੁ ਸਾਚੁ ਕਹੈ ਬੇਨੰਤੀ ਮਿਲਿ ਸਾਚੇ ਸੁਖੁ ਪਾਇਦਾ ॥੧੬॥੨॥੧੪॥",
   "translit": "naanak saach kahai benantee mil saache sukh paaeidaa |16|2|14|",
   "english": "Nanak offers this true prayer; meeting with the True Lord, peace is obtained. ||16||2||14||",
   "shabadId": "F8D"
  },
  {
   "gurmukhi": "ਮਾਰੂ ਮਹਲਾ ੧ ॥",
   "translit": "maaroo mahalaa 1 |",
   "english": "Maaroo, First Mehl:",
   "shabadId": "7MZ"
  },
  {
   "gurmukhi": "ਅਰਬਦ ਨਰਬਦ ਧੁੰਧੂਕਾਰਾ ॥",
   "translit": "arabad narabad dhundhookaaraa |",
   "english": "For endless eons, there was only utter darkness.",
   "shabadId": "7MZ"
  },
  {
   "gurmukhi": "ਧਰਣਿ ਨ ਗਗਨਾ ਹੁਕਮੁ ਅਪਾਰਾ ॥",
   "translit": "dharan na gaganaa hukam apaaraa |",
   "english": "There was no earth or sky; there was only the infinite Command of His Hukam.",
   "shabadId": "7MZ"
  },
  {
   "gurmukhi": "ਨਾ ਦਿਨੁ ਰੈਨਿ ਨ ਚੰਦੁ ਨ ਸੂਰਜੁ ਸੁੰਨ ਸਮਾਧਿ ਲਗਾਇਦਾ ॥੧॥",
   "translit": "naa din rain na chand na sooraj sun samaadh lagaaeidaa |1|",
   "english": "There was no day or night, no moon or sun; God sat in primal, profound Samaadhi. ||1||",
   "shabadId": "7MZ"
  },
  {
   "gurmukhi": "ਓਪਤਿ ਖਪਤਿ ਨ ਆਵਣ ਜਾਣੀ ॥",
   "translit": "opat khapat na aavan jaanee |",
   "english": "There was no creation or destruction, no coming or going.",
   "shabadId": "7MZ"
  },
  {
   "gurmukhi": "ਖਾਣੀ ਨ ਬਾਣੀ ਪਉਣ ਨ ਪਾਣੀ ॥",
   "translit": "khaanee na baanee paun na paanee |",
   "english": "There were no sources of creation or powers of speech, no air or water.",
   "shabadId": "7MZ"
  },
  {
   "gurmukhi": "ਖੰਡ ਪਤਾਲ ਸਪਤ ਨਹੀ ਸਾਗਰ ਨਦੀ ਨ ਨੀਰੁ ਵਹਾਇਦਾ ॥੨॥",
   "translit": "khandd pataal sapat nahee saagar nadee na neer vahaaeidaa |2|",
   "english": "There were no continents, nether regions, seven seas, rivers or flowing water. ||2||",
   "shabadId": "7MZ"
  },
  {
   "gurmukhi": "ਨਾ ਤਦਿ ਸੁਰਗੁ ਮਛੁ ਪਇਆਲਾ ॥",
   "translit": "naa tad surag machh peaalaa |",
   "english": "There were no heavenly realms, earth or nether regions of the underworld.",
   "shabadId": "7MZ"
  },
  {
   "gurmukhi": "ਦੋਜਕੁ ਭਿਸਤੁ ਨਹੀ ਖੈ ਕਾਲਾ ॥",
   "translit": "dojak bhisat nahee khai kaalaa |",
   "english": "There was no heaven or hell, no death or time.",
   "shabadId": "7MZ"
  },
  {
   "gurmukhi": "ਨਰਕੁ ਸੁਰਗੁ ਨਹੀ ਜੰਮਣੁ ਮਰਣਾ ਨਾ ਕੋ ਆਇ ਨ ਜਾਇਦਾ ॥੩॥",
   "translit": "narak surag nahee jaman maranaa naa ko aae na jaaeidaa |3|",
   "english": "There was no hell or heaven, no birth or death, no coming or going in reincarnation. ||3||",
   "shabadId": "7MZ"
  },
  {
   "gurmukhi": "ਬ੍ਰਹਮਾ ਬਿਸਨੁ ਮਹੇਸੁ ਨ ਕੋਈ ॥",
   "translit": "brahamaa bisan mahes na koee |",
   "english": "There was no Brahma, Vishnu or Shiva.",
   "shabadId": "7MZ"
  },
  {
   "gurmukhi": "ਅਵਰੁ ਨ ਦੀਸੈ ਏਕੋ ਸੋਈ ॥",
   "translit": "avar na deesai eko soee |",
   "english": "No one was seen, except the One Lord.",
   "shabadId": "7MZ"
  },
  {
   "gurmukhi": "ਨਾ ਤਦਿ ਜਤੀ ਸਤੀ ਬਨਵਾਸੀ ॥",
   "translit": "naa tad jatee satee banavaasee |",
   "english": "There were no people of celibacy or charity; no one lived in the forests.",
   "shabadId": "7MZ"
  },
  {
   "gurmukhi": "ਨਾਰਿ ਪੁਰਖੁ ਨਹੀ ਜਾਤਿ ਨ ਜਨਮਾ ਨਾ ਕੋ ਦੁਖੁ ਸੁਖੁ ਪਾਇਦਾ ॥੪॥",
   "translit": "naar purakh nahee jaat na janamaa naa ko dukh sukh paaeidaa |4|",
   "english": "There was no female or male, no social class or caste of birth; no one experienced pain or pleasure. ||4||",
   "shabadId": "7MZ"
  },
  {
   "gurmukhi": "ਜਪ ਤਪ ਸੰਜਮ ਨਾ ਬ੍ਰਤ ਪੂਜਾ ॥",
   "translit": "jap tap sanjam naa brat poojaa |",
   "english": "There was no chanting or meditation, no self-discipline, fasting or worship.",
   "shabadId": "7MZ"
  },
  {
   "gurmukhi": "ਨਾ ਤਦਿ ਸਿਧ ਸਾਧਿਕ ਸੁਖਵਾਸੀ ॥",
   "translit": "naa tad sidh saadhik sukhavaasee |",
   "english": "There were no Siddhas or seekers, no one living in peace.",
   "shabadId": "7MZ"
  },
  {
   "gurmukhi": "ਜੋਗੀ ਜੰਗਮ ਭੇਖੁ ਨ ਕੋਈ ਨਾ ਕੋ ਨਾਥੁ ਕਹਾਇਦਾ ॥੫॥",
   "translit": "jogee jangam bhekh na koee naa ko naath kahaaeidaa |5|",
   "english": "There were no Yogis, no wandering pilgrims, no religious robes; no one called himself the master. ||5||",
   "shabadId": "7MZ"
  },
  {
   "gurmukhi": "ਨਾ ਸੁਚਿ ਸੰਜਮੁ ਤੁਲਸੀ ਮਾਲਾ ॥",
   "translit": "naa such sanjam tulasee maalaa |",
   "english": "There was no purification, no self-restraint, no malas of basil seeds.",
   "shabadId": "7MZ"
  },
  {
   "gurmukhi": "ਨਾ ਕੋ ਆਖਿ ਵਖਾਣੈ ਦੂਜਾ ॥",
   "translit": "naa ko aakh vakhaanai doojaa |",
   "english": "No one spoke or talked in duality.",
   "shabadId": "7MZ"
  },
  {
   "gurmukhi": "ਆਪੇ ਆਪਿ ਉਪਾਇ ਵਿਗਸੈ ਆਪੇ ਕੀਮਤਿ ਪਾਇਦਾ ॥੬॥",
   "translit": "aape aap upaae vigasai aape keemat paaeidaa |6|",
   "english": "He created Himself, and rejoiced; He evaluates Himself. ||6||",
   "shabadId": "7MZ"
  },
  {
   "gurmukhi": "ਤੰਤੁ ਮੰਤੁ ਪਾਖੰਡੁ ਨ ਕੋਈ ਨਾ ਕੋ ਵੰਸੁ ਵਜਾਇਦਾ ॥੭॥",
   "translit": "tant mant paakhandd na koee naa ko vans vajaaeidaa |7|",
   "english": "There were no tantras, no mantras and no hypocrisy; no one played the flute. ||7||",
   "shabadId": "7MZ"
  },
  {
   "gurmukhi": "ਗੋਪੀ ਕਾਨੁ ਨ ਗਊ ਗੋੁਆਲਾ ॥",
   "translit": "gopee kaan na gaoo gouaalaa |",
   "english": "There were no Gopis, no Krishna, no cows or cowherds.",
   "shabadId": "7MZ"
  },
  {
   "gurmukhi": "ਕਰਮ ਧਰਮ ਨਹੀ ਮਾਇਆ ਮਾਖੀ ॥",
   "translit": "karam dharam nahee maaeaa maakhee |",
   "english": "There was no karma, no Dharma, no buzzing fly of Maya.",
   "shabadId": "7MZ"
  },
  {
   "gurmukhi": "ਜਾਤਿ ਜਨਮੁ ਨਹੀ ਦੀਸੈ ਆਖੀ ॥",
   "translit": "jaat janam nahee deesai aakhee |",
   "english": "Social class and birth were not seen with any eyes.",
   "shabadId": "7MZ"
  },
  {
   "gurmukhi": "ਮਮਤਾ ਜਾਲੁ ਕਾਲੁ ਨਹੀ ਮਾਥੈ ਨਾ ਕੋ ਕਿਸੈ ਧਿਆਇਦਾ ॥੮॥",
   "translit": "mamataa jaal kaal nahee maathai naa ko kisai dhiaaeidaa |8|",
   "english": "There was no noose of attachment, no death inscribed upon the forehead; no one meditated on anything. ||8||",
   "shabadId": "7MZ"
  },
  {
   "gurmukhi": "ਨਿੰਦੁ ਬਿੰਦੁ ਨਹੀ ਜੀਉ ਨ ਜਿੰਦੋ ॥",
   "translit": "nind bind nahee jeeo na jindo |",
   "english": "There was no slander, no seed, no soul and no life.",
   "shabadId": "7MZ"
  },
  {
   "gurmukhi": "ਨਾ ਤਦਿ ਗਿਆਨੁ ਧਿਆਨੁ ਕੁਲ ਓਪਤਿ ਨਾ ਕੋ ਗਣਤ ਗਣਾਇਦਾ ॥੯॥",
   "translit": "naa tad giaan dhiaan kul opat naa ko ganat ganaaeidaa |9|",
   "english": "There was no spiritual wisdom or meditation, no ancestry or creation, no reckoning of accounts. ||9||",
   "shabadId": "7MZ"
  },
  {
   "gurmukhi": "ਨਾ ਤਦਿ ਗੋਰਖੁ ਨਾ ਮਾਛਿੰਦੋ ॥",
   "translit": "naa tad gorakh naa maachhindo |",
   "english": "There was no Gorakh and no Maachhindra.",
   "shabadId": "7MZ"
  }
 ]
}